{
    "type": "weapon",
    "id": "b7ab0c0dec13a2bdb991cd9a",
    "name": "M4A1 T4 4",
    "root": "1edad3e4e3630fb1832204bc",
    "items": [
        {
            "_id": "1edad3e4e3630fb1832204bc",
            "_tpl": "5447a9cd4bdc2dbd208b4567",
            "upd": {
                "Repairable": {
                    "MaxDurability": 100,
                    "Durability": 100
                },
                "FireMode": {
                    "FireMode": "single"
                }
            }
        },
        {
            "_id": "5de5672267627439c4097ab6",
            "_tpl": "59db3a1d86f77429e05b4e92",
            "parentId": "1edad3e4e3630fb1832204bc",
            "slotId": "mod_pistol_grip"
        },
        {
            "_id": "703434aa24c2f14ef24fb2ae",
            "_tpl": "544a37c44bdc2d25388b4567",
            "parentId": "1edad3e4e3630fb1832204bc",
            "slotId": "mod_magazine"
        },
        {
            "_id": "edef576bf6f8c6112fb23547",
            "_tpl": "59bfe68886f7746004266202",
            "parentId": "1edad3e4e3630fb1832204bc",
            "slotId": "mod_reciever"
        },
        {
            "_id": "b5c0f85f59c4e3b4af65f3fc",
            "_tpl": "5c793fb92e221644f31bfb64",
            "parentId": "1edad3e4e3630fb1832204bc",
            "slotId": "mod_stock"
        },
        {
            "_id": "1008bc100115154b3776dfe4",
            "_tpl": "5b2240bf5acfc40dc528af69",
            "parentId": "1edad3e4e3630fb1832204bc",
            "slotId": "mod_charge"
        },
        {
            "_id": "a86febc84e72916cccc96d70",
            "_tpl": "58491f3324597764bc48fa02",
            "parentId": "edef576bf6f8c6112fb23547",
            "slotId": "mod_scope",
            "upd": {
                "Sight": {
                    "ScopesCurrentCalibPointIndexes": [0],
                    "ScopesSelectedModes": [0],
                    "SelectedScope": 0
                }
            }
        },
        {
            "_id": "5141e8d2e96598c3db0efaf3",
            "_tpl": "63d3d44a2a49307baf09386d",
            "parentId": "edef576bf6f8c6112fb23547",
            "slotId": "mod_barrel"
        },
        {
            "_id": "b9f70c471e4a19cd23cc5774",
            "_tpl": "5b2cfa535acfc432ff4db7a0",
            "parentId": "edef576bf6f8c6112fb23547",
            "slotId": "mod_handguard"
        },
        {
            "_id": "28e6323ddb2b1929c430ede3",
            "_tpl": "5fb6564947ce63734e3fa1da",
            "parentId": "edef576bf6f8c6112fb23547",
            "slotId": "mod_sight_rear",
            "upd": {
                "Sight": {
                    "ScopesCurrentCalibPointIndexes": [0],
                    "ScopesSelectedModes": [0],
                    "SelectedScope": 0
                }
            }
        },
        {
            "_id": "f54c0e19f293dbed4abba427",
            "_tpl": "58d2946c86f7744e271174b5",
            "parentId": "b5c0f85f59c4e3b4af65f3fc",
            "slotId": "mod_stock_000"
        },
        {
            "_id": "0c68a15ddd0ff6cd89e5424c",
            "_tpl": "609269c3b0e443224b421cc1",
            "parentId": "5141e8d2e96598c3db0efaf3",
            "slotId": "mod_muzzle"
        },
        {
            "_id": "8f1b7a3d80b56b5353c5e741",
            "_tpl": "63d3ce281fe77d0f2801859e",
            "parentId": "5141e8d2e96598c3db0efaf3",
            "slotId": "mod_gas_block"
        },
        {
            "_id": "a969699424e8df6d0b5f81b5",
            "_tpl": "5b30bc285acfc47a8608615d",
            "parentId": "b9f70c471e4a19cd23cc5774",
            "slotId": "mod_mount_000"
        },
        {
            "_id": "2486f31f0e0754d3014b7903",
            "_tpl": "60926df0132d4d12c81fd9df",
            "parentId": "0c68a15ddd0ff6cd89e5424c",
            "slotId": "mod_muzzle"
        },
        {
            "_id": "bbe7e938095eb6f2a96eb144",
            "_tpl": "5a7dbfc1159bd40016548fde",
            "parentId": "a969699424e8df6d0b5f81b5",
            "slotId": "mod_foregrip"
        },
        {
            "_id": "c774e0c9d093dab4cc899572",
            "_tpl": "56def37dd2720bec348b456a",
            "parentId": "a969699424e8df6d0b5f81b5",
            "slotId": "mod_tactical",
            "upd": {
                "Light": {
                    "IsActive": true,
                    "SelectedMode": 0
                }
            }
        },
        {
            "_id": "7a0bb9452609c621b962d589",
            "_tpl": "58d2912286f7744e27117493",
            "parentId": "f54c0e19f293dbed4abba427",
            "slotId": "mod_stock"
        }
    ],
    "Parent": "5447b5f14bdc2d61278b4567"
}
