{
    "type": "weapon",
    "id": "94dbb67a3e7b65ff55e16656",
    "name": "MDR 545 T4 9",
    "root": "e4c8e13c6d0c4afd69c659e5",
    "items": [
        {
            "_id": "e4c8e13c6d0c4afd69c659e5",
            "_tpl": "5c488a752e221602b412af63",
            "upd": {
                "Repairable": {
                    "MaxDurability": 100,
                    "Durability": 100
                },
                "FireMode": {
                    "FireMode": "single"
                }
            }
        },
        {
            "_id": "5c6e0fe152e1abf744669a53",
            "_tpl": "5c48a2c22e221602b313fb6c",
            "parentId": "e4c8e13c6d0c4afd69c659e5",
            "slotId": "mod_pistol_grip"
        },
        {
            "_id": "3cd8a546bff4799eec8c81f3",
            "_tpl": "55802d5f4bdc2dac148b458e",
            "parentId": "e4c8e13c6d0c4afd69c659e5",
            "slotId": "mod_magazine"
        },
        {
            "_id": "815136b49e9ea2541121c6c9",
            "_tpl": "5c48a14f2e2216152006edd7",
            "parentId": "e4c8e13c6d0c4afd69c659e5",
            "slotId": "mod_handguard"
        },
        {
            "_id": "43035666f7ebb49c02a5dc6f",
            "_tpl": "5c48a2852e221602b21d5923",
            "parentId": "e4c8e13c6d0c4afd69c659e5",
            "slotId": "mod_barrel"
        },
        {
            "_id": "92390bdea33389b42b7cdf21",
            "_tpl": "5b3b99265acfc4704b4a1afb",
            "parentId": "e4c8e13c6d0c4afd69c659e5",
            "slotId": "mod_scope"
        },
        {
            "_id": "d285c5329afb04d55140f83c",
            "_tpl": "5fb6564947ce63734e3fa1da",
            "parentId": "e4c8e13c6d0c4afd69c659e5",
            "slotId": "mod_sight_rear",
            "upd": {
                "Sight": {
                    "ScopesCurrentCalibPointIndexes": [0],
                    "ScopesSelectedModes": [0],
                    "SelectedScope": 0
                }
            }
        },
        {
            "_id": "50756374fe52d24b675bf93b",
            "_tpl": "5b7be4895acfc400170e2dd5",
            "parentId": "815136b49e9ea2541121c6c9",
            "slotId": "mod_mount_000"
        },
        {
            "_id": "3598cc5d91f0d54c6a1887de",
            "_tpl": "5b7be47f5acfc400170e2dd2",
            "parentId": "815136b49e9ea2541121c6c9",
            "slotId": "mod_mount_001"
        },
        {
            "_id": "c4a4d9717fee4864f15063cc",
            "_tpl": "609269c3b0e443224b421cc1",
            "parentId": "43035666f7ebb49c02a5dc6f",
            "slotId": "mod_muzzle"
        },
        {
            "_id": "1df37ea4bd42311480d8d762",
            "_tpl": "5b3b99475acfc432ff4dcbee",
            "parentId": "92390bdea33389b42b7cdf21",
            "slotId": "mod_scope",
            "upd": {
                "Sight": {
                    "ScopesCurrentCalibPointIndexes": [0],
                    "ScopesSelectedModes": [0],
                    "SelectedScope": 0
                }
            }
        },
        {
            "_id": "d9b5bdd1f2bec2af2b96ef03",
            "_tpl": "5b057b4f5acfc4771e1bd3e9",
            "parentId": "50756374fe52d24b675bf93b",
            "slotId": "mod_foregrip"
        },
        {
            "_id": "a37b9efb137544f02216a61f",
            "_tpl": "626becf9582c3e319310b837",
            "parentId": "3598cc5d91f0d54c6a1887de",
            "slotId": "mod_tactical",
            "upd": {
                "Light": {
                    "IsActive": true,
                    "SelectedMode": 0
                }
            }
        },
        {
            "_id": "c01e2db5ed1e1528ac293811",
            "_tpl": "60926df0132d4d12c81fd9df",
            "parentId": "c4a4d9717fee4864f15063cc",
            "slotId": "mod_muzzle"
        }
    ],
    "Parent": "5447b5f14bdc2d61278b4567"
}
