{
    "type": "weapon",
    "id": "85443360a989def7c1261971",
    "name": "HK 416A5 T3 3",
    "root": "be4b71e1cb13068caf52f618",
    "items": [
        {
            "_id": "be4b71e1cb13068caf52f618",
            "_tpl": "5bb2475ed4351e00853264e3",
            "upd": {
                "Repairable": {
                    "MaxDurability": 100,
                    "Durability": 100
                },
                "FireMode": {
                    "FireMode": "single"
                }
            }
        },
        {
            "_id": "874be73ab369466540a37f6a",
            "_tpl": "6113c3586c780c1e710c90bc",
            "parentId": "be4b71e1cb13068caf52f618",
            "slotId": "mod_pistol_grip"
        },
        {
            "_id": "debfc69ca7839d1376d1f27d",
            "_tpl": "5d1340cad7ad1a0b0b249869",
            "parentId": "be4b71e1cb13068caf52f618",
            "slotId": "mod_magazine"
        },
        {
            "_id": "dbcadc50c095f50e284e5933",
            "_tpl": "5bb20d53d4351e4502010a69",
            "parentId": "be4b71e1cb13068caf52f618",
            "slotId": "mod_reciever"
        },
        {
            "_id": "2ece2af0b4c1a8aef78442a0",
            "_tpl": "5bb20e58d4351e00320205d7",
            "parentId": "be4b71e1cb13068caf52f618",
            "slotId": "mod_stock"
        },
        {
            "_id": "9652484d69e917f57e6b51f7",
            "_tpl": "5ea16d4d5aad6446a939753d",
            "parentId": "be4b71e1cb13068caf52f618",
            "slotId": "mod_charge"
        },
        {
            "_id": "7f9e2aa8a2a7fc138fdf0f56",
            "_tpl": "58491f3324597764bc48fa02",
            "parentId": "dbcadc50c095f50e284e5933",
            "slotId": "mod_scope",
            "upd": {
                "Sight": {
                    "ScopesCurrentCalibPointIndexes": [0],
                    "ScopesSelectedModes": [0],
                    "SelectedScope": 0
                }
            }
        },
        {
            "_id": "92867de624a5bcde46555e0a",
            "_tpl": "5bb20da5d4351e0035629dbf",
            "parentId": "dbcadc50c095f50e284e5933",
            "slotId": "mod_barrel"
        },
        {
            "_id": "22cb602cd0d1a072e8c874df",
            "_tpl": "5c6d10fa2e221600106f3f23",
            "parentId": "dbcadc50c095f50e284e5933",
            "slotId": "mod_handguard"
        },
        {
            "_id": "ba6abccb825dadbda7639bd5",
            "_tpl": "5c18b9192e2216398b5a8104",
            "parentId": "dbcadc50c095f50e284e5933",
            "slotId": "mod_sight_rear",
            "upd": {
                "Sight": {
                    "ScopesCurrentCalibPointIndexes": [0],
                    "ScopesSelectedModes": [0],
                    "SelectedScope": 0
                }
            }
        },
        {
            "_id": "2ba61b5951de18291c76b863",
            "_tpl": "58d2946386f774496974c37e",
            "parentId": "2ece2af0b4c1a8aef78442a0",
            "slotId": "mod_stock_000"
        },
        {
            "_id": "65d3a012e523e5cb146268dc",
            "_tpl": "612e0cfc8004cc50514c2d9e",
            "parentId": "92867de624a5bcde46555e0a",
            "slotId": "mod_muzzle"
        },
        {
            "_id": "0bfaf050d21c2bf01fe13a2e",
            "_tpl": "5bb20dcad4351e3bac1212da",
            "parentId": "92867de624a5bcde46555e0a",
            "slotId": "mod_gas_block"
        },
        {
            "_id": "fbf909d6ae7d411dcb115e29",
            "_tpl": "5b7be47f5acfc400170e2dd2",
            "parentId": "22cb602cd0d1a072e8c874df",
            "slotId": "mod_mount_001"
        },
        {
            "_id": "e3ed03d29d062799ad43d8af",
            "_tpl": "5b7be4895acfc400170e2dd5",
            "parentId": "22cb602cd0d1a072e8c874df",
            "slotId": "mod_foregrip"
        },
        {
            "_id": "619d1910a6f46ff583d51170",
            "_tpl": "5c18b90d2e2216152142466b",
            "parentId": "22cb602cd0d1a072e8c874df",
            "slotId": "mod_sight_front",
            "upd": {
                "Sight": {
                    "ScopesCurrentCalibPointIndexes": [0],
                    "ScopesSelectedModes": [0],
                    "SelectedScope": 0
                }
            }
        },
        {
            "_id": "9e84f03024ab531b1df1a4bf",
            "_tpl": "63877c99e785640d436458ea",
            "parentId": "65d3a012e523e5cb146268dc",
            "slotId": "mod_muzzle"
        },
        {
            "_id": "fff456f93fc26de53b13661c",
            "_tpl": "6272379924e29f06af4d5ecb",
            "parentId": "fbf909d6ae7d411dcb115e29",
            "slotId": "mod_tactical",
            "upd": {
                "Light": {
                    "IsActive": true,
                    "SelectedMode": 0
                }
            }
        },
        {
            "_id": "328347ad1431436945cd3632",
            "_tpl": "5fce0cf655375d18a253eff0",
            "parentId": "e3ed03d29d062799ad43d8af",
            "slotId": "mod_foregrip"
        },
        {
            "_id": "ae8dfc3445b12063a80b0c52",
            "_tpl": "58d2912286f7744e27117493",
            "parentId": "2ba61b5951de18291c76b863",
            "slotId": "mod_stock"
        }
    ],
    "Parent": "5447b5f14bdc2d61278b4567"
}
