{
    "type": "weapon",
    "id": "c7f3ad91f65087abb87ea2c9",
    "name": "MP9 T2 1",
    "root": "6a456734b096c788f32cb118",
    "items": [
        {
            "_id": "6a456734b096c788f32cb118",
            "_tpl": "5e00903ae9dc277128008b87",
            "upd": {
                "Repairable": {
                    "MaxDurability": 100,
                    "Durability": 100
                },
                "Foldable": {
                    "Folded": false
                },
                "FireMode": {
                    "FireMode": "single"
                }
            }
        },
        {
            "_id": "89797fa62f027e34bbbb3234",
            "_tpl": "5de8eac42a78646d96665d91",
            "parentId": "6a456734b096c788f32cb118",
            "slotId": "mod_magazine"
        },
        {
            "_id": "37bc430cccca960fdc12624b",
            "_tpl": "5de8f237bbaf010b10528a70",
            "parentId": "6a456734b096c788f32cb118",
            "slotId": "mod_muzzle"
        },
        {
            "_id": "7228d0f4450eed7a720e6b07",
            "_tpl": "5de910da8b6c4240ba2651b5",
            "parentId": "6a456734b096c788f32cb118",
            "slotId": "mod_stock"
        },
        {
            "_id": "be3f1dd44fff2490f983634b",
            "_tpl": "5e0090f7e9dc277128008b93",
            "parentId": "6a456734b096c788f32cb118",
            "slotId": "mod_reciever"
        },
        {
            "_id": "79f23bc388c49aa1e891ecf5",
            "_tpl": "5de922d4b11454561e39239f",
            "parentId": "6a456734b096c788f32cb118",
            "slotId": "mod_charge"
        },
        {
            "_id": "2e5d8210b7bc87e78787c207",
            "_tpl": "5de8fbf2b74cd90030650c79",
            "parentId": "6a456734b096c788f32cb118",
            "slotId": "mod_mount_000"
        },
        {
            "_id": "7c65083d9327fdb16f068ab2",
            "_tpl": "5de8f2d5b74cd90030650c72",
            "parentId": "37bc430cccca960fdc12624b",
            "slotId": "mod_muzzle"
        },
        {
            "_id": "c3eb71dc7a1e2333dd83035c",
            "_tpl": "58491f3324597764bc48fa02",
            "parentId": "be3f1dd44fff2490f983634b",
            "slotId": "mod_scope",
            "upd": {
                "Sight": {
                    "ScopesCurrentCalibPointIndexes": [0],
                    "ScopesSelectedModes": [0],
                    "SelectedScope": 0
                }
            }
        },
        {
            "_id": "f397cb37680b79c7a5b6b5d7",
            "_tpl": "5de8fb539f98ac2bc659513a",
            "parentId": "be3f1dd44fff2490f983634b",
            "slotId": "mod_sight_rear",
            "upd": {
                "Sight": {
                    "ScopesCurrentCalibPointIndexes": [0],
                    "ScopesSelectedModes": [0],
                    "SelectedScope": 0
                }
            }
        },
        {
            "_id": "12b4737cd4ac709bbdd8add8",
            "_tpl": "5de8fc0b205ddc616a6bc51b",
            "parentId": "be3f1dd44fff2490f983634b",
            "slotId": "mod_mount"
        },
        {
            "_id": "039e46442660e1296ad5be91",
            "_tpl": "5c1bc5fb2e221602b1779b32",
            "parentId": "2e5d8210b7bc87e78787c207",
            "slotId": "mod_foregrip"
        },
        {
            "_id": "c506528ca5786427c66e652f",
            "_tpl": "56def37dd2720bec348b456a",
            "parentId": "12b4737cd4ac709bbdd8add8",
            "slotId": "mod_tactical",
            "upd": {
                "Light": {
                    "IsActive": true,
                    "SelectedMode": 0
                }
            }
        }
    ],
    "Parent": "5447b5e04bdc2d62278b4567"
}
